include/tmxlite/Config.hpp
include/tmxlite/FreeFuncs.hpp
include/tmxlite/ImageLayer.hpp
include/tmxlite/Layer.hpp
include/tmxlite/LayerGroup.hpp
include/tmxlite/Map.hpp
include/tmxlite/Object.hpp
include/tmxlite/ObjectGroup.hpp
include/tmxlite/ObjectTypes.hpp
include/tmxlite/Property.hpp
include/tmxlite/TileLayer.hpp
include/tmxlite/Tileset.hpp
include/tmxlite/Types.hpp
include/tmxlite/Types.inl
include/tmxlite/detail/Android.hpp
include/tmxlite/detail/Log.hpp
lib64/libtmxlite-s.a
lib64/pkgconfig/tmxlite.pc
pykraken/__init__.py
pykraken/__init__.pyi
pykraken/_core.cpython-311-x86_64-linux-gnu.so
pykraken/fx.py
pykraken/shader_uniform.py
pykraken/__pyinstaller/hook-pykraken.py
pykraken/_core/__init__.pyi
pykraken/_core/collision.pyi
pykraken/_core/color.pyi
pykraken/_core/draw.pyi
pykraken/_core/ease.pyi
pykraken/_core/event.pyi
pykraken/_core/gamepad.pyi
pykraken/_core/input.pyi
pykraken/_core/key.pyi
pykraken/_core/line.pyi
pykraken/_core/log.pyi
pykraken/_core/math.pyi
pykraken/_core/mouse.pyi
pykraken/_core/pixel_array.pyi
pykraken/_core/rect.pyi
pykraken/_core/renderer.pyi
pykraken/_core/tilemap.pyi
pykraken/_core/time.pyi
pykraken/_core/transform.pyi
pykraken/_core/viewport.pyi
pykraken/_core/window.pyi
kraken_engine-1.6.0.dist-info/METADATA
kraken_engine-1.6.0.dist-info/WHEEL
kraken_engine-1.6.0.dist-info/RECORD
kraken_engine-1.6.0.dist-info/licenses/LICENSE
