Metadata-Version: 2.4
Name: kraken-engine
Version: 1.6.0
Summary: Python bindings for Kraken Engine
Author: Derrick Martinez
License-Expression: MIT
License-File: LICENSE
Classifier: Programming Language :: Python
Classifier: Programming Language :: Python :: 3
Classifier: Programming Language :: Python :: 3.11
Classifier: Programming Language :: Python :: 3.12
Classifier: Programming Language :: Python :: 3.13
Classifier: Programming Language :: Python :: 3.14
Classifier: Topic :: Games/Entertainment
Classifier: Topic :: Multimedia :: Graphics
Classifier: Operating System :: Microsoft :: Windows
Classifier: Operating System :: MacOS
Classifier: Operating System :: POSIX :: Linux
Project-URL: Homepage, https://docs.krakenengine.org/
Project-URL: Issues, https://github.com/Kraken-Engine/PyKraken/issues
Project-URL: Documentation, https://docs.krakenengine.org/docs/getting-started/introduction
Project-URL: Release Notes, https://github.com/Kraken-Engine/PyKraken/releases
Project-URL: Source, https://github.com/Kraken-Engine/PyKraken
Requires-Python: >=3.11
Requires-Dist: pydantic==2.12.3
